Workbook

Sheet CRM de Leads
A1: SATTURNEX | CRM DE PROSPECÇÃO COMERCIAL
A2: Clientes potenciais • Navegantes/SC • Registre cada interação e mantenha o próximo passo definido.
A4: ID | B4: Negócio | C4: Segmento | D4: Cidade | E4: Telefone listado | F4: Instagram / rede social | G4: Site atual | H4: Site verificado? | I4: Fonte | J4: Prioridade | K4: Responsável Satturnex | L4: Etapa comercial | M4: Último contato | N4: Próxima ação | O4: Data follow-up | P4: Serviço de interesse | Q4: Valor ofertado (R$) | R4: Valor fechado (R$) | S4: Chance (%) | T4: Notas da conversa | U4: Dados conferidos?
A5: 1 | B5: Barbearia 660 | C5: Barbearia | D5: Navegantes, SC | E5: (47) 99927-7233 | H5: Não verificado | I5: https://www.solutudo.com.br/empresas/sc/navegantes/barbearias | J5: Alta | K5: A definir | L5: Não contatado | N5: Pesquisar Instagram e site | S5: 20 | T5: Confirmar telefone, Instagram e se já possui site próprio. | U5: Pendente
A6: 2 | B6: Gui Barber Shop | C6: Barbearia | D6: Navegantes, SC | E6: (47) 99968-0543 | H6: Não verificado | I6: https://www.solutudo.com.br/empresas/sc/navegantes/barbearias | J6: Alta | K6: A definir | L6: Não contatado | N6: Pesquisar Instagram e site | S6: 20 | T6: Confirmar telefone, Instagram e se já possui site próprio. | U6: Pendente
A7: 3 | B7: Dênis New Barber Shop | C7: Barbearia | D7: Navegantes, SC | E7: (47) 98413-7742 | H7: Não verificado | I7: https://www.solutudo.com.br/empresas/sc/navegantes/barbearias | J7: Alta | K7: A definir | L7: Não contatado | N7: Pesquisar Instagram e site | S7: 20 | T7: Confirmar telefone, Instagram e se já possui site próprio. | U7: Pendente
A8: 4 | B8: Barbearia Eloi | C8: Barbearia | D8: Navegantes, SC | E8: (47) 98472-9644 | H8: Não verificado | I8: https://www.solutudo.com.br/empresas/sc/navegantes/barbearias | J8: Alta | K8: A definir | L8: Não contatado | N8: Pesquisar Instagram e site | S8: 20 | T8: Confirmar telefone, Instagram e se já possui site próprio. | U8: Pendente
A9: 5 | B9: JAMES Barbearia | C9: Barbearia | D9: Navegantes, SC | E9: (47) 99108-4929 | H9: Não verificado | I9: https://www.solutudo.com.br/empresas/sc/navegantes/barbearias | J9: Alta | K9: A definir | L9: Não contatado | N9: Pesquisar Instagram e site | S9: 20 | T9: Confirmar telefone, Instagram e se já possui site próprio. | U9: Pendente
A10: 6 | B10: Thay Krause Designer de Unhas | C10: Beleza / unhas | D10: Navegantes, SC | E10: (47) 98432-1226* | H10: Não verificado | I10: https://www.solutudo.com.br/empresas/sc/navegantes/manicures%2Be%2Bpedicures | J10: Alta | K10: A definir | L10: Não contatado | N10: Pesquisar Instagram e site | S10: 20 | T10: Telefone marcado com *; confirmar na fonte original antes de usar. | U10: Pendente
A11: 7 | B11: Ana Cleude Ribeiro — manicure | C11: Beleza / unhas | D11: Navegantes, SC | E11: (47) 99994-9194 | H11: Não verificado | I11: https://www.solutudo.com.br/empresas/sc/navegantes/manicures%2Be%2Bpedicures | J11: Alta | K11: A definir | L11: Não contatado | N11: Pesquisar Instagram e site | S11: 20 | T11: Confirmar telefone, Instagram e se já possui site próprio. | U11: Pendente
A12: 8 | B12: Studio N.A. | C12: Beleza | D12: Navegantes, SC | E12: (47) 99619-7921* | H12: Não verificado | I12: https://www.solutudo.com.br/empresas/sc/navegantes/manicures%2Be%2Bpedicures | J12: Alta | K12: A definir | L12: Não contatado | N12: Pesquisar Instagram e site | S12: 20 | T12: Telefone marcado com *; confirmar na fonte original antes de usar. | U12: Pendente
A13: 9 | B13: NT Motopeças | C13: Motopeças | D13: Navegantes, SC | E13: (47) 99920-8478 | H13: Não verificado | I13: https://www.solutudo.com.br/empresas/sc/navegantes/oficinas%2Bmotos | J13: Média | K13: A definir | L13: Não contatado | N13: Pesquisar Instagram e site | S13: 20 | T13: Verificar se catálogo digital ou página institucional seria útil. | U13: Pendente
A14: 10 | B14: Garagem Motos | C14: Oficina de motos | D14: Navegantes, SC | E14: (47) 99661-5356 | H14: Não verificado | I14: https://www.solutudo.com.br/empresas/sc/navegantes/oficinas%2Bmotos | J14: Média | K14: A definir | L14: Não contatado | N14: Pesquisar Instagram e site | S14: 20 | T14: Confirmar contato e presença digital. | U14: Pendente
A15: 11 | B15: JS Motos | C15: Oficina de motos | D15: Navegantes, SC | E15: (47) 99680-0616* | H15: Não verificado | I15: https://www.solutudo.com.br/empresas/sc/navegantes/oficinas%2Bmotos | J15: Média | K15: A definir | L15: Não contatado | N15: Pesquisar Instagram e site | S15: 20 | T15: Telefone marcado com *; confirmar na fonte original antes de usar. | U15: Pendente
A16: 12 | B16: Fire Motos Oficina | C16: Oficina de motos | D16: Navegantes, SC | E16: (47) 98480-8192* | H16: Não verificado | I16: https://www.solutudo.com.br/empresas/sc/navegantes/oficinas%2Bmotos | J16: Média | K16: A definir | L16: Não contatado | N16: Pesquisar Instagram e site | S16: 20 | T16: Telefone marcado com *; confirmar na fonte original antes de usar. | U16: Pendente
... A24: 20 | B24: Sabor Caseiro | C24: Alimentação | D24: Navegantes, SC | E24: (47) 99622-2373* | H24: Não verificado | I24: https://www.solutudo.com.br/empresas/sc/navegantes/marmitarias | J24: Média | K24: A definir | L24: Não contatado | N24: Pesquisar Instagram e site | S24: 20 | T24: Telefone marcado com *; confirmar na fonte original. | U24: Pendente

Sheet Painel
A1: SATTURNEX | PAINEL COMERCIAL
A2: Visão rápida do funil, das responsabilidades e da meta de vendas.
A4: Indicador | B4: Resultado | D4: Etapa comercial | E4: Quantidade | G4: Responsável | H4: Leads
A5: Leads na lista | B5: =COUNTA('CRM de Leads'!B5:B24) -> 20 | D5: Não contatado | E5: =COUNTIF('CRM de Leads'!L5:L24,D5) -> 20 | G5: Gustavo | H5: =COUNTIF('CRM de Leads'!K5:K24,G5) -> 0
A6: Ainda não contatados | B6: =COUNTIF('CRM de Leads'!L5:L24,"Não contatado") -> 20 | D6: Contato enviado | E6: =COUNTIF('CRM de Leads'!L5:L24,D6) -> 0 | G6: Manel | H6: =COUNTIF('CRM de Leads'!K5:K24,G6) -> 0
A7: Contatos enviados | B7: =COUNTIF('CRM de Leads'!L5:L24,"Contato enviado") -> 0 | D7: Respondeu | E7: =COUNTIF('CRM de Leads'!L5:L24,D7) -> 0 | G7: Ambos | H7: =COUNTIF('CRM de Leads'!K5:K24,G7) -> 0
A8: Respostas / qualificados | B8: =COUNTIF('CRM de Leads'!L5:L24,"Respondeu")+COUNTIF('CRM de Leads'!L5:L24,"Qualificado") -> 0 | D8: Qualificado | E8: =COUNTIF('CRM de Leads'!L5:L24,D8) -> 0 | G8: A definir | H8: =COUNTIF('CRM de Leads'!K5:K24,G8) -> 20
A9: Demonstrações solicitadas | B9: =COUNTIF('CRM de Leads'!L5:L24,"Demonstração solicitada") -> 0 | D9: Demonstração solicitada | E9: =COUNTIF('CRM de Leads'!L5:L24,D9) -> 0
A10: Propostas enviadas | B10: =COUNTIF('CRM de Leads'!L5:L24,"Proposta enviada") -> 0 | D10: Reunião marcada | E10: =COUNTIF('CRM de Leads'!L5:L24,D10) -> 0
A11: Clientes fechados | B11: =COUNTIF('CRM de Leads'!L5:L24,"Fechado") -> 0 | D11: Proposta enviada | E11: =COUNTIF('CRM de Leads'!L5:L24,D11) -> 0
A12: Valor total fechado | B12: =SUM('CRM de Leads'!R5:R24) -> 0 | D12: Negociação | E12: =COUNTIF('CRM de Leads'!L5:L24,D12) -> 0
A13: Meta inicial | B13: 1000 | D13: Fechado | E13: =COUNTIF('CRM de Leads'!L5:L24,D13) -> 0
A14: Falta para a meta | B14: =MAX(0,B12-B11) -> 0 | D14: Perdido | E14: =COUNTIF('CRM de Leads'!L5:L24,D14) -> 0
A15: Follow-ups vencidos | B15: =COUNTIFS('CRM de Leads'!O5:O24,"<"&TODAY(),'CRM de Leads'!O5:O24,">0",'CRM de Leads'!L5:L24,"<>Fechado",'CRM de Leads'!L5:L24,"<>Perdido") -> 0 | D15: Sem retorno | E15: =COUNTIF('CRM de Leads'!L5:L24,D15) -> 0
A18: Rotina sugerida
A19: 1. Manel: prioriza o contato inicial e registra respostas e objeções.
A20: 2. Gustavo: apoia com demonstrações, escopo, estimativas e execução técnica.
A21: 3. Definam o responsável por cada lead antes de enviar mensagem para evitar duplicidade.
A22: 4. Não marque 'Não tem site' sem conferir Google, Instagram e o site informado pelo negócio.
A23: 5. Todo contato deve terminar com uma próxima ação e uma data de follow-up.
A26: Divisão dos projetos | B26: 50% Gustavo / 50% Manel
A28: Calculadora de divisão (preencha custos)
A29: Receita recebida (R$) | B29: 0
A30: Custos do projeto (R$) | B30: 0
A31: Resultado líquido (R$) | B31: =B29-B30 -> 0
A32: Parte do Gustavo (50%) | B32: =MAX(0,B31)*50% -> 0
A33: Parte do Manel (50%) | B33: =MAX(0,B31)*50% -> 0

Sheet Mensagens
A1: SATTURNEX | BIBLIOTECA DE MENSAGENS
A2: Personalize com o nome do negócio e um detalhe real. Evite disparos genéricos.
A4: 1. Primeira abordagem (WhatsApp)
A5: Olá! Tudo bem? Aqui é [NOME] da Satturnex. A gente desenvolve soluções digitais para pequenos negócios. Conheci o perfil da [EMPRESA] e queria entender se hoje vocês usam algum site ou página para apresentar os serviços e receber contatos. Posso te fazer uma pergunta rápida?
A9: 2. Se responder que não tem site
A10: Entendi! A ideia não é complicar a rotina de vocês: podemos montar uma página profissional, adaptada ao celular, com serviços, fotos, localização e um botão direto para o WhatsApp. Se fizer sentido, posso te mostrar uma demonstração visual para a [EMPRESA].
A14: 3. Se já tiver Instagram, mas não site
A15: Legal, o Instagram ajuda bastante. Um site pode complementar isso reunindo serviços, informações e formas de contato em um só lugar, sem substituir as redes sociais. Hoje vocês sentem falta de alguma coisa que seria útil para os clientes encontrarem mais facilmente?
A19: 4. Follow-up após 2–3 dias
A20: Oi! Tudo bem? Passando para retomar minha mensagem sobre a presença digital da [EMPRESA]. Se melhorar a apresentação dos serviços ou facilitar os contatos estiver nos planos de vocês, posso mostrar uma ideia objetiva. Se não for prioridade agora, sem problema.
A24: 5. Quando demonstrar interesse
A25: Perfeito! Para eu sugerir algo que realmente faça sentido, me conta rapidinho: qual serviço ou produto vocês mais querem divulgar e qual ação gostariam que o cliente fizesse — chamar no WhatsApp, pedir orçamento, agendar ou consultar um catálogo?
... A60: O domínio é o endereço do seu site, enquanto a hospedagem é o serviço que mantém o site disponível na internet. São custos separados do desenvolvimento e podem ter cobranças recorrentes para manter o site funcionando.

Sheet Acordo da dupla
A1: SATTURNEX | FLUXO DE TRABALHO DA DUPLA
A3: Atividade | B3: Responsável sugerido | C3: O que registrar | D3: Quando passar para o outro
A4: Pesquisa e qualificação | B4: Ambos | C4: Site atual, Instagram, contato válido, necessidade provável | D4: Quando o lead estiver conferido
A5: Primeiro contato e conversa | B5: Manel | C5: Data, resposta, necessidade, objeções e próximo passo | D5: Quando houver interesse ou pedido de demonstração
A6: Demonstração e solução técnica | B6: Gustavo | C6: Ideia visual, escopo, funcionalidades e limitações | D6: Após validar a necessidade com o cliente
A7: Proposta e negociação | B7: Manel + Gustavo | C7: Preço, escopo, prazo, pagamento e validade da proposta | D7: Antes de confirmar o fechamento
A8: Execução do projeto | B8: Gustavo (com apoio combinado) | C8: Materiais recebidos, tarefas, aprovações e entregas | D8: Em cada marco acordado
A9: Pós-venda e indicação | B9: Manel | C9: Satisfação, ajustes combinados e possibilidade de indicação | D9: Após a entrega
A12: Regra prática: cada lead tem um responsável principal. A divisão financeira dos projetos será 50/50 entre Gustavo e Manel, conforme o acordo. Registrem custos e recebimentos antes de calcular o valor líquido.

Sheet Custo de Referencia
A1: SATTURNEX | CUSTOS DE DOMÍNIO E HOSPEDAGEM
A2: Referências para orçamento e negociação • Valores consultados em outubro/2026 • Promoções podem mudar.
A4: Item / provedor | B4: Tipo | C4: Preço divulgado | D4: Equivalente mensal | E4: Observação importante | F4: Fonte oficial
A5: Registro.br (.com.br) | B5: Domínio | C5: R$ 40.00 | D5: R$ 3.33 | E5: R$ 40 por ano. Renovação anual; domínio normalmente fica em nome do cliente. | F5: https://registro.br/dominio
A6: Hostinger Single | B6: Hospedagem compartilhada | C6: R$ 5.99 | D6: R$ 5.99 | E6: Preço promocional equivalente mensal em contratação de 48 meses; renovação divulgada: R$ 23,99/mês. Pagamento antecipado do ciclo. | F6: https://www.hostinger.com/br/hospedagem-de-sites
A7: Hostinger Premium | B7: Hospedagem compartilhada | C7: R$ 10.99 | D7: R$ 10.99 | E7: Preço promocional equivalente mensal em contratação de 48 meses; renovação divulgada: R$ 38,99/mês. Domínio grátis pode valer só no primeiro ano. | F7: https://www.hostinger.com/br/hospedagem-de-sites
A8: Locaweb Go | B8: Hospedagem compartilhada | C8: R$ 5.90 | D8: R$ 5.90 | E8: Oferta divulgada a partir de R$ 5,90/mês com pagamento integral e antecipado; preço cheio exibido: R$ 24,90/mês. | F8: https://hm9613.locaweb.com.br/hospedagem-de-sites-com-dominio-gratis/
A9: HostGator Start | B9: Hospedagem compartilhada | C9: R$ 25.89 | D9: R$ 25.89 | E9: Referência de preço regular anual: R$ 310,29/ano, equivalente a R$ 25,89/mês; confira o ciclo e preço vigente antes de contratar. | F9: https://www.hostgator.com.br/precos-hostgator
A12: Atenção: preço promocional não é o custo real de longo prazo. Compare o total pago no ciclo e a taxa de renovação antes de fechar.
A16: Resumo | B16: Dominio
A17: É o endereço que as pessoas digitam para acessar um site, como minhaempresa.com.br. Funciona como o endereço de uma loja física e normalmente é pago por ano.
A18: Exemplo de custo: renovação anual do endereço.
A20: Resumo | B20: Hospedagem
A21: É o serviço que mantém os arquivos do site disponíveis na internet para que qualquer pessoa possa acessá-lo. Pode ser gratuito ou pago, dependendo da tecnologia e dos recursos utilizados.
A22: Exemplo de custo: mensalidade ou plano anual.

Sheet Negociar
A1: SATTURNEX | COMO APRESENTAR OS CUSTOS
A2: Modelo simples para explicar o que é custo de terceiros e evitar que a empresa absorva renovações sem combinar.
A4: Cenário | B4: Referência para planejar | C4: Como apresentar ao cliente | D4: Recomendação
A5: Domínio .com.br | B5: R$ 40/ano (≈ R$ 3,33/mês) | C5: Registro e renovação do domínio: custo anual de terceiros. | D5: Preferível registrar no CPF/CNPJ do cliente, com acesso dele.
A6: Hospedagem básica | B6: Planejar R$ 10–30/mês; validar renovação | C6: Hospedagem é recorrente e pode variar conforme plano e promoção. | D6: Informe preço promocional, prazo contratado e preço de renovação separadamente.
A7: Site simples com hospedagem do cliente | B7: Cliente paga diretamente ao provedor | C7: O orçamento do site cobre desenvolvimento; domínio/hospedagem são contratados à parte. | D7: Mais transparente e reduz risco de custos recorrentes para a Satturnex.
A8: Satturnex administra a hospedagem | B8: Cobrar custo + taxa de gestão definida | C8: Mensalidade inclui infraestrutura e o serviço de administração acordado. | D8: Especificar suporte, backups, atualizações, limites e prazo de resposta.
A9: Projeto com custo anual antecipado | B9: Mostrar total anual e equivalente mensal | C9: Ex.: domínio R$ 40/ano + hospedagem conforme plano escolhido. | D9: Não prometa preço fixo sem confirmar renovação e impostos/taxas.
A12: Sugestão comercial: se o cliente quer pagar rápido, separe o valor do desenvolvimento dos custos de domínio/hospedagem. Receba o desenvolvimento conforme o combinado e deixe explícito quem renova os serviços.

Sheet Calculadora
A1: SATTURNEX | CALCULADORA DE CUSTO RECORRENTE
A2: Altere as células amarelas para estimar custo de primeiro ano e custo recorrente. Valores são referências, não cotação garantida.
A4: Campo | B4: Valor | C4: Orientação
A5: Domínio por ano (R$) | B5: R$ 40.00 | C5: Referência Registro.br .com.br
A6: Hospedagem mensal (R$) | B6: R$ 25.89 | C6: Use o preço de renovação/contrato aplicável, não só a promoção
A7: Meses de hospedagem no cálculo | B7: 12 | C7: Normalmente 12 para estimar um ano
A8: Taxa de administração mensal (R$) | B8: R$ 0.00 | C8: Opcional: valor cobrado pela Satturnex para administrar o serviço
A9: Custo anual de domínio | B9: R$ 40.00 | C9: Custo anual estimado
A10: Custo de hospedagem no período | B10: R$ 310.68 | C10: Mensalidade multiplicada pelos meses
A11: Administração no período | B11: R$ 0.00 | C11: Se houver taxa de gestão
A12: CUSTO TOTAL ESTIMADO | B12: R$ 350.68 | C12: Não inclui desenvolvimento, impostos ou taxas adicionais
A13: Equivalente mensal total | B13: R$ 29.22 | C13: Total dividido pelo período escolhido

Sheet Finanças
A1: SATTURNEX | CONTROLE FINANCEIRO
A2: Registre entradas e custos abaixo. O painel calcula os valores recebidos/pagos e a divisão 50/50.
A4: ENTRADAS RECEBIDAS | C4: CUSTOS PAGOS | E4: RESULTADO LÍQUIDO | G4: PARTE DE CADA SÓCIO
A5: R$ 0.00 | C5: R$ 0.00 | E5: R$ 0.00 | G5: R$ 0.00
A7: CUSTO FIXO PADRÃO
A8: Despesa | B8: Valor total | C8: Periodicidade | D8: Reserva mensal | E8: Equivalente anual | F8: Próximo vencimento | G8: Observação
A9: Domínio Satturnex | B9: 112 | C9: A cada 3 anos | D9: R$ 4.42 | E9: R$ 53.00 | G9: R$ 112,00 por ciclo de 3 anos
A11: LANÇAMENTOS DE ENTRADAS E CUSTOS
A12: Use valores positivos. Entradas recebidas e custos pagos entram no resumo; pendências ficam registradas sem alterar o caixa realizado.
A17: Data | B17: Cliente / descrição | C17: Tipo | D17: Categoria | E17: Valor (R$) | F17: Situação | G17: Observações
A27: RESUMO MENSAL
A28: Mês (1º dia) | B28: Entradas recebidas | C28: Custos pagos | D28: Resultado | E28: Gustavo (50%) | F28: Manel (50%)
A29: 46023 | B29: R$ 0.00 | C29: R$ 0.00 | D29: R$ 0.00 | E29: R$ 0.00 | F29: R$ 0.00
A30: Feb/2026 | B30: R$ 0.00 | C30: R$ 0.00 | D30: R$ 0.00 | E30: R$ 0.00 | F30: R$ 0.00
A31: 46082 | B31: R$ 0.00 | C31: R$ 0.00 | D31: R$ 0.00 | E31: R$ 0.00 | F31: R$ 0.00
A32: Apr/2026 | B32: R$ 0.00 | C32: R$ 0.00 | D32: R$ 0.00 | E32: R$ 0.00 | F32: R$ 0.00
A33: May/2026 | B33: R$ 0.00 | C33: R$ 0.00 | D33: R$ 0.00 | E33: R$ 0.00 | F33: R$ 0.00
A34: 46174 | B34: R$ 0.00 | C34: R$ 0.00 | D34: R$ 0.00 | E34: R$ 0.00 | F34: R$ 0.00
A35: 46204 | B35: R$ 0.00 | C35: R$ 0.00 | D35: R$ 0.00 | E35: R$ 0.00 | F35: R$ 0.00
A36: Aug/2026 | B36: R$ 0.00 | C36: R$ 0.00 | D36: R$ 0.00 | E36: R$ 0.00 | F36: R$ 0.00
A37: Sep/2026 | B37: R$ 0.00 | C37: R$ 0.00 | D37: R$ 0.00 | E37: R$ 0.00 | F37: R$ 0.00
A38: Oct/2026 | B38: R$ 0.00 | C38: R$ 0.00 | D38: R$ 0.00 | E38: R$ 0.00 | F38: R$ 0.00
A39: 46327 | B39: R$ 0.00 | C39: R$ 0.00 | D39: R$ 0.00 | E39: R$ 0.00 | F39: R$ 0.00
A40: Dec/2026 | B40: R$ 0.00 | C40: R$ 0.00 | D40: R$ 0.00 | E40: R$ 0.00 | F40: R$ 0.00
A43: RETIRADAS DOS SÓCIOS
A44: Data | B44: Sócio | C44: Referência / mês | D44: Valor retirado (R$) | E44: Pago? | F44: Observações
